Metadata-Version: 2.1
Name: telly
Version: 0.9.1
Summary: telly - simple, privacy-friendly usage statistics for your open source software
Home-page: https://github.com/telly-llc/
Author: Telly LLC
Author-email: it@gotelly.io
Maintainer: Telly LLC
License: Apache-2.0
Keywords: telly,telemetry,statistics,privacy,open source,usage
Classifier: Intended Audience :: Developers
Classifier: License :: OSI Approved :: Apache Software License
Classifier: Natural Language :: English
Classifier: Programming Language :: Python :: 2
Classifier: Programming Language :: Python :: 3
Classifier: Programming Language :: Python :: 2.6
Classifier: Programming Language :: Python :: 2.7
Classifier: Programming Language :: Python :: 3.4
Classifier: Programming Language :: Python :: 3.5
Classifier: Programming Language :: Python :: 3.6
Classifier: Programming Language :: Python :: 3.7
Classifier: Programming Language :: Python :: 3.8
Classifier: Programming Language :: Python :: 3.9
Classifier: Programming Language :: Python :: 3.10
Classifier: Programming Language :: Python :: 3.11
Classifier: Programming Language :: Python :: Implementation :: CPython
Classifier: Programming Language :: Python :: Implementation :: PyPy
Classifier: Development Status :: 4 - Beta
Requires-Python: >=2.7
License-File: LICENSE
